yellowstone_fumarole_client/__init__.py
yellowstone_fumarole_client/config.py
yellowstone_fumarole_client/error.py
yellowstone_fumarole_client/grpc_connectivity.py
yellowstone_fumarole_client/runtime/__init__.py
yellowstone_fumarole_client/runtime/aio.py
yellowstone_fumarole_client/runtime/state_machine.py
yellowstone_fumarole_client/utils/__init__.py
yellowstone_fumarole_client/utils/aio.py
yellowstone_fumarole_client/utils/collections.py
yellowstone_fumarole_proto/__init__.py
yellowstone_fumarole_proto/fumarole_pb2.py
yellowstone_fumarole_proto/fumarole_pb2.pyi
yellowstone_fumarole_proto/fumarole_pb2_grpc.py
yellowstone_fumarole_proto/geyser_pb2.py
yellowstone_fumarole_proto/geyser_pb2.pyi
yellowstone_fumarole_proto/geyser_pb2_grpc.py
yellowstone_fumarole_proto/solana_storage_pb2.py
yellowstone_fumarole_proto/solana_storage_pb2.pyi
yellowstone_fumarole_proto/solana_storage_pb2_grpc.py
yellowstone_fumarole_client-0.3.2.dist-info/METADATA
yellowstone_fumarole_client-0.3.2.dist-info/WHEEL
yellowstone_fumarole_client-0.3.2.dist-info/RECORD
