Metadata-Version: 2.1
Name: yellowstone-fumarole-client
Version: 0.3.2
Summary: Yellowstone Fumarole Python Client
Home-page: https://github.com/rpcpool/yellowstone-fumarole
Author: Louis-Vincent
Author-email: louis-vincent@triton.one
Requires-Python: >=3.13,<4.0
Classifier: Programming Language :: Python :: 3
Classifier: Programming Language :: Python :: 3.13
Requires-Dist: grpcio (>=1.71.1,<2.0.0)
Requires-Dist: protobuf (>=6.32.0,<7.0.0)
Requires-Dist: pyyaml (>=6.0.2,<7.0.0)
Project-URL: Repository, https://github.com/rpcpool/yellowstone-fumarole
